test/__init__.py
test/trivyscan_test.py
trivyscan/__init__.py
trivyscan/bin/__init__.py
trivyscan/bin/trivy
trivyscan/bin/trivy.zip
trivyscan/src/__init__.py
trivyscan/src/trivyscan.py
trivyscan-0.0.8.dist-info/METADATA
trivyscan-0.0.8.dist-info/WHEEL
trivyscan-0.0.8.dist-info/top_level.txt
trivyscan-0.0.8.dist-info/RECORD
