Metadata-Version: 2.1
Name: trivyscan
Version: 0.0.8
Summary: A Python package to run Trivy security scans on Docker images, including the Trivy binary.
Home-page: https://github.com/alaxalves/trivyscan
Author: Alax Alves
Author-email: alaxallves@gmail.com
License: UNKNOWN
Platform: UNKNOWN
Classifier: Programming Language :: Python :: 3
Classifier: License :: OSI Approved :: MIT License
Classifier: Operating System :: OS Independent
Requires-Python: >=3.9
